normie_alternatives/__init__.py
normie_alternatives/abram_steg/__init__.py
normie_alternatives/abram_steg/erf.py
normie_alternatives/wichura/__init__.py
normie_alternatives/wichura/erf.py
normie_alternatives-0.2.0.dist-info/METADATA
normie_alternatives-0.2.0.dist-info/WHEEL
normie_alternatives-0.2.0.dist-info/RECORD
